idasen_controller/__init__.py
idasen_controller/config.py
idasen_controller/desk.py
idasen_controller/example/config.yaml
idasen_controller/gatt.py
idasen_controller/main.py
idasen_controller/util.py
idasen_controller-2.2.0.dist-info/LICENSE
idasen_controller-2.2.0.dist-info/METADATA
idasen_controller-2.2.0.dist-info/WHEEL
idasen_controller-2.2.0.dist-info/RECORD
